bulgogi.cpython-310-aarch64-linux-gnu.so
bulgogi-0.1.5.dist-info/LICENSE
bulgogi-0.1.5.dist-info/WHEEL
bulgogi-0.1.5.dist-info/METADATA
bulgogi-0.1.5.dist-info/top_level.txt
bulgogi-0.1.5.dist-info/RECORD
