Metadata-Version: 2.1
Name: bulgogi
Version: 0.1.5
Summary: A flexible build system assistant.
Author-email: Alex Amellal <bulgogi@alexamellal.com>
Project-URL: Homepage, https://bulgogi.dev
Project-URL: Issues, https://github.com/high-intensity-prototyping-labs/bulgogi-py/issues
Classifier: Development Status :: 2 - Pre-Alpha
Classifier: Programming Language :: C
Classifier: Intended Audience :: Developers
Classifier: Operating System :: MacOS
Classifier: Topic :: Software Development :: Build Tools
Requires-Python: >=3.8
License-File: LICENSE
